openvas_parser/__init__.py
openvas_parser/parser.py
openvas_xml_parser-1.0.0.dist-info/licenses/LICENSE
openvas_xml_parser-1.0.0.dist-info/METADATA
openvas_xml_parser-1.0.0.dist-info/WHEEL
openvas_xml_parser-1.0.0.dist-info/entry_points.txt
openvas_xml_parser-1.0.0.dist-info/top_level.txt
openvas_xml_parser-1.0.0.dist-info/RECORD
