Metadata-Version: 2.4
Name: openvas-xml-parser
Version: 1.0.0
Summary: Convert OpenVAS XML reports to structured JSON format
Home-page: https://github.com/Haseeb-1698/CyberPulse
Author: Haseeb-1698
Author-email: haseeb@example.com
Project-URL: Bug Reports, https://github.com/Haseeb-1698/CyberPulse/issues
Project-URL: Source, https://github.com/Haseeb-1698/CyberPulse
Project-URL: Documentation, https://github.com/Haseeb-1698/CyberPulse#readme
Keywords: openvas,xml,json,security,vulnerability,scanning
Classifier: Development Status :: 4 - Beta
Classifier: Intended Audience :: Information Technology
Classifier: Intended Audience :: System Administrators
Classifier: License :: OSI Approved :: MIT License
Classifier: Operating System :: OS Independent
Classifier: Programming Language :: Python :: 3
Classifier: Programming Language :: Python :: 3.8
Classifier: Programming Language :: Python :: 3.9
Classifier: Programming Language :: Python :: 3.10
Classifier: Programming Language :: Python :: 3.11
Classifier: Topic :: Security
Classifier: Topic :: Software Development :: Libraries :: Python Modules
Classifier: Topic :: Text Processing :: Markup :: XML
Requires-Python: >=3.8
License-File: LICENSE
Requires-Dist: lxml>=4.9.0
Dynamic: author
Dynamic: author-email
Dynamic: classifier
Dynamic: description
Dynamic: description-content-type
Dynamic: home-page
Dynamic: keywords
Dynamic: license-file
Dynamic: project-url
Dynamic: requires-dist
Dynamic: requires-python
Dynamic: summary
